nalibsExam/__init__.py
nalibsExam/__version.py
nalibsExam/example.py
nalibs_exam-0.2.0.dist-info/LICENSE
nalibs_exam-0.2.0.dist-info/METADATA
nalibs_exam-0.2.0.dist-info/WHEEL
nalibs_exam-0.2.0.dist-info/top_level.txt
nalibs_exam-0.2.0.dist-info/RECORD
