Metadata-Version: 2.1
Name: nalibs-exam
Version: 0.2.0
Summary: qana - tiny package - nalibsExam
Author-email: Ron <naq0310@gmail.com>
Maintainer-email: Ron <naq0310@gmail.com>
Project-URL: Homepage, https://github.com/pypa/sampleproject
Project-URL: Issues, https://github.com/pypa/sampleproject/issues
Classifier: Programming Language :: Python :: 3
Classifier: License :: OSI Approved :: MIT License
Classifier: Operating System :: OS Independent
Requires-Python: >=3.9
License-File: LICENSE
